odoo/addons/edi_record_metadata_oca/README.rst
odoo/addons/edi_record_metadata_oca/__init__.py
odoo/addons/edi_record_metadata_oca/__manifest__.py
odoo/addons/edi_record_metadata_oca/fields.py
odoo/addons/edi_record_metadata_oca/i18n/edi_record_metadata_oca.pot
odoo/addons/edi_record_metadata_oca/models/__init__.py
odoo/addons/edi_record_metadata_oca/models/edi_exchange_consumer_mixin.py
odoo/addons/edi_record_metadata_oca/models/edi_exchange_record.py
odoo/addons/edi_record_metadata_oca/readme/CONTRIBUTORS.rst
odoo/addons/edi_record_metadata_oca/readme/DESCRIPTION.rst
odoo/addons/edi_record_metadata_oca/readme/USAGE.rst
odoo/addons/edi_record_metadata_oca/static/description/icon.png
odoo/addons/edi_record_metadata_oca/static/description/index.html
odoo/addons/edi_record_metadata_oca/tests/__init__.py
odoo/addons/edi_record_metadata_oca/tests/fake_models.py
odoo/addons/edi_record_metadata_oca/tests/test_metadata.py
odoo/addons/edi_record_metadata_oca/views/edi_exchange_record.xml
odoo14_addon_edi_record_metadata_oca-14.0.1.2.0.dist-info/METADATA
odoo14_addon_edi_record_metadata_oca-14.0.1.2.0.dist-info/WHEEL
odoo14_addon_edi_record_metadata_oca-14.0.1.2.0.dist-info/top_level.txt
odoo14_addon_edi_record_metadata_oca-14.0.1.2.0.dist-info/RECORD
